[{"place_id": 20997454, "licence": "Data \u00a9 OpenStreetMap contributors, ODbL 1.0. http://osm.org/copyright", "osm_type": "relation", "osm_id": 8802299, "lat": "45.6606073", "lon": "-73.5253145", "class": "boundary", "type": "administrative", "place_rank": 20, "importance": 0.374579673985169, "addresstype": "suburb", "name": "Rivi\u00e8re-des-Prairies\u2013Pointe-aux-Trembles", "display_name": "Rivi\u00e8re-des-Prairies\u2013Pointe-aux-Trembles, Montreal, Urban agglomeration of Montreal, Montreal (administrative region), Quebec, Canada", "boundingbox": ["45.6125908", "45.7047897", "-73.6238275", "-73.4742952"]}]